Metadata-Version: 1.1
Name: memoized-property
Version: 1.0.1
Summary: A simple python decorator for defining properties that only run their fget function once
Home-page: https://github.com/estebistec/python-memoized-property
Author: Steven Cummings
Author-email: cummingscs@gmail.com
License: BSD
Keywords: memoized property decorator
Platform: UNKNOWN
Classifier: Development Status :: 5 - Production/Stable
Classifier: Intended Audience :: Developers
Classifier: License :: OSI Approved :: BSD License
Classifier: Natural Language :: English
Classifier: Programming Language :: Python :: 2
Classifier: Programming Language :: Python :: 2.6
Classifier: Programming Language :: Python :: 2.7
Classifier: Programming Language :: Python :: 3
Classifier: Programming Language :: Python :: 3.2
Classifier: Programming Language :: Python :: 3.3
